[{"iconClass":"fa-folder","objectID":"https://aidanbae.github.io/categories/algorithm","title":"Algorithm","type":"category","url":"https://aidanbae.github.io/categories/algorithm"},{"iconClass":"fa-folder","objectID":"https://aidanbae.github.io/categories/blog","title":"Blog","type":"category","url":"https://aidanbae.github.io/categories/blog"},{"iconClass":"fa-folder","objectID":"https://aidanbae.github.io/categories/book","title":"Book","type":"category","url":"https://aidanbae.github.io/categories/book"},{"iconClass":"fa-folder","objectID":"https://aidanbae.github.io/categories/code","title":"Code","type":"category","url":"https://aidanbae.github.io/categories/code"},{"iconClass":"fa-folder","objectID":"https://aidanbae.github.io/categories/devops","title":"Devops","type":"category","url":"https://aidanbae.github.io/categories/devops"},{"iconClass":"fa-folder","objectID":"https://aidanbae.github.io/categories/docker","title":"Docker","type":"category","url":"https://aidanbae.github.io/categories/docker"},{"iconClass":"fa-folder","objectID":"https://aidanbae.github.io/categories/golang","title":"Golang","type":"category","url":"https://aidanbae.github.io/categories/golang"},{"iconClass":"fa-folder","objectID":"https://aidanbae.github.io/categories/hugo","title":"Hugo","type":"category","url":"https://aidanbae.github.io/categories/hugo"},{"iconClass":"fa-folder","objectID":"https://aidanbae.github.io/categories/javascript","title":"Javascript","type":"category","url":"https://aidanbae.github.io/categories/javascript"},{"iconClass":"fa-folder","objectID":"https://aidanbae.github.io/categories/linux","title":"Linux","type":"category","url":"https://aidanbae.github.io/categories/linux"},{"iconClass":"fa-folder","objectID":"https://aidanbae.github.io/categories/movie","title":"Movie","type":"category","url":"https://aidanbae.github.io/categories/movie"},{"iconClass":"fa-folder","objectID":"https://aidanbae.github.io/categories/music","title":"Music","type":"category","url":"https://aidanbae.github.io/categories/music"},{"iconClass":"fa-folder","objectID":"https://aidanbae.github.io/categories/python","title":"Python","type":"category","url":"https://aidanbae.github.io/categories/python"},{"iconClass":"fa-folder","objectID":"https://aidanbae.github.io/categories/server","title":"Server","type":"category","url":"https://aidanbae.github.io/categories/server"},{"iconClass":"fa-folder","objectID":"https://aidanbae.github.io/categories/shell","title":"Shell","type":"category","url":"https://aidanbae.github.io/categories/shell"},{"iconClass":"fa-folder","objectID":"https://aidanbae.github.io/categories/smalltalk","title":"Smalltalk","type":"category","url":"https://aidanbae.github.io/categories/smalltalk"},{"iconClass":"fa-folder","objectID":"https://aidanbae.github.io/categories/wisdom","title":"Wisdom","type":"category","url":"https://aidanbae.github.io/categories/wisdom"},{"iconClass":"fa-user","objectID":"https://aidanbae.github.io/author/aidan.bae","title":"Aidan.bae","type":"author","url":"https://aidanbae.github.io/author/aidan.bae"},{"iconClass":"fa-user","objectID":"https://aidanbae.github.io/author/george-vaillant","title":"George vaillant","type":"author","url":"https://aidanbae.github.io/author/george-vaillant"},{"iconClass":"fa-user","objectID":"https://aidanbae.github.io/author/%EB%8F%88%ED%82%A4%ED%98%B8%ED%85%8C-%EB%A7%A8%EC%98%A4%EB%B8%8C%EB%9D%BC%EB%A7%8C%EC%B0%A8","title":"돈키호테 맨오브라만차","type":"author","url":"https://aidanbae.github.io/author/%EB%8F%88%ED%82%A4%ED%98%B8%ED%85%8C-%EB%A7%A8%EC%98%A4%EB%B8%8C%EB%9D%BC%EB%A7%8C%EC%B0%A8"},{"iconClass":"fa-tag","objectID":"https://aidanbae.github.io/tags/","title":"","type":"tag","url":"https://aidanbae.github.io/tags/"},{"iconClass":"fa-tag","objectID":"https://aidanbae.github.io/tags/agent","title":"Agent","type":"tag","url":"https://aidanbae.github.io/tags/agent"},{"iconClass":"fa-tag","objectID":"https://aidanbae.github.io/tags/algorithm","title":"Algorithm","type":"tag","url":"https://aidanbae.github.io/tags/algorithm"},{"iconClass":"fa-tag","objectID":"https://aidanbae.github.io/tags/array","title":"Array","type":"tag","url":"https://aidanbae.github.io/tags/array"},{"iconClass":"fa-tag","objectID":"https://aidanbae.github.io/tags/atomic","title":"Atomic","type":"tag","url":"https://aidanbae.github.io/tags/atomic"},{"iconClass":"fa-tag","objectID":"https://aidanbae.github.io/tags/aws-cli","title":"Aws cli","type":"tag","url":"https://aidanbae.github.io/tags/aws-cli"},{"iconClass":"fa-tag","objectID":"https://aidanbae.github.io/tags/bash","title":"Bash","type":"tag","url":"https://aidanbae.github.io/tags/bash"},{"iconClass":"fa-tag","objectID":"https://aidanbae.github.io/tags/benchmark-test","title":"Benchmark test","type":"tag","url":"https://aidanbae.github.io/tags/benchmark-test"},{"iconClass":"fa-tag","objectID":"https://aidanbae.github.io/tags/big-o","title":"Big o","type":"tag","url":"https://aidanbae.github.io/tags/big-o"},{"iconClass":"fa-tag","objectID":"https://aidanbae.github.io/tags/computer-science","title":"Computer science","type":"tag","url":"https://aidanbae.github.io/tags/computer-science"},{"iconClass":"fa-tag","objectID":"https://aidanbae.github.io/tags/console","title":"Console","type":"tag","url":"https://aidanbae.github.io/tags/console"},{"iconClass":"fa-tag","objectID":"https://aidanbae.github.io/tags/console.log","title":"Console.log","type":"tag","url":"https://aidanbae.github.io/tags/console.log"},{"iconClass":"fa-tag","objectID":"https://aidanbae.github.io/tags/console.time","title":"Console.time","type":"tag","url":"https://aidanbae.github.io/tags/console.time"},{"iconClass":"fa-tag","objectID":"https://aidanbae.github.io/tags/console.timeend","title":"Console.timeend","type":"tag","url":"https://aidanbae.github.io/tags/console.timeend"},{"iconClass":"fa-tag","objectID":"https://aidanbae.github.io/tags/cpu-cache","title":"Cpu cache","type":"tag","url":"https://aidanbae.github.io/tags/cpu-cache"},{"iconClass":"fa-tag","objectID":"https://aidanbae.github.io/tags/cpu-%EC%BA%90%EC%8B%9C","title":"Cpu 캐시","type":"tag","url":"https://aidanbae.github.io/tags/cpu-%EC%BA%90%EC%8B%9C"},{"iconClass":"fa-tag","objectID":"https://aidanbae.github.io/tags/day-1","title":"Day 1","type":"tag","url":"https://aidanbae.github.io/tags/day-1"},{"iconClass":"fa-tag","objectID":"https://aidanbae.github.io/tags/dcos","title":"Dcos","type":"tag","url":"https://aidanbae.github.io/tags/dcos"},{"iconClass":"fa-tag","objectID":"https://aidanbae.github.io/tags/debug","title":"Debug","type":"tag","url":"https://aidanbae.github.io/tags/debug"},{"iconClass":"fa-tag","objectID":"https://aidanbae.github.io/tags/deploy","title":"Deploy","type":"tag","url":"https://aidanbae.github.io/tags/deploy"},{"iconClass":"fa-tag","objectID":"https://aidanbae.github.io/tags/design-pattern","title":"Design pattern","type":"tag","url":"https://aidanbae.github.io/tags/design-pattern"},{"iconClass":"fa-tag","objectID":"https://aidanbae.github.io/tags/devops","title":"Devops","type":"tag","url":"https://aidanbae.github.io/tags/devops"},{"iconClass":"fa-tag","objectID":"https://aidanbae.github.io/tags/docker","title":"Docker","type":"tag","url":"https://aidanbae.github.io/tags/docker"},{"iconClass":"fa-tag","objectID":"https://aidanbae.github.io/tags/docker-client","title":"Docker client","type":"tag","url":"https://aidanbae.github.io/tags/docker-client"},{"iconClass":"fa-tag","objectID":"https://aidanbae.github.io/tags/docker-container","title":"Docker container","type":"tag","url":"https://aidanbae.github.io/tags/docker-container"},{"iconClass":"fa-tag","objectID":"https://aidanbae.github.io/tags/docker-daemon","title":"Docker daemon","type":"tag","url":"https://aidanbae.github.io/tags/docker-daemon"},{"iconClass":"fa-tag","objectID":"https://aidanbae.github.io/tags/empty-struct","title":"Empty struct","type":"tag","url":"https://aidanbae.github.io/tags/empty-struct"},{"iconClass":"fa-tag","objectID":"https://aidanbae.github.io/tags/fan-in","title":"Fan in","type":"tag","url":"https://aidanbae.github.io/tags/fan-in"},{"iconClass":"fa-tag","objectID":"https://aidanbae.github.io/tags/fan-out","title":"Fan out","type":"tag","url":"https://aidanbae.github.io/tags/fan-out"},{"iconClass":"fa-tag","objectID":"https://aidanbae.github.io/tags/fever","title":"Fever","type":"tag","url":"https://aidanbae.github.io/tags/fever"},{"iconClass":"fa-tag","objectID":"https://aidanbae.github.io/tags/filter","title":"Filter","type":"tag","url":"https://aidanbae.github.io/tags/filter"},{"iconClass":"fa-tag","objectID":"https://aidanbae.github.io/tags/find","title":"Find","type":"tag","url":"https://aidanbae.github.io/tags/find"},{"iconClass":"fa-tag","objectID":"https://aidanbae.github.io/tags/findindex","title":"Findindex","type":"tag","url":"https://aidanbae.github.io/tags/findindex"},{"iconClass":"fa-tag","objectID":"https://aidanbae.github.io/tags/foreach","title":"Foreach","type":"tag","url":"https://aidanbae.github.io/tags/foreach"},{"iconClass":"fa-tag","objectID":"https://aidanbae.github.io/tags/garbage-collector","title":"Garbage collector","type":"tag","url":"https://aidanbae.github.io/tags/garbage-collector"},{"iconClass":"fa-tag","objectID":"https://aidanbae.github.io/tags/github","title":"Github","type":"tag","url":"https://aidanbae.github.io/tags/github"},{"iconClass":"fa-tag","objectID":"https://aidanbae.github.io/tags/go-module","title":"Go module","type":"tag","url":"https://aidanbae.github.io/tags/go-module"},{"iconClass":"fa-tag","objectID":"https://aidanbae.github.io/tags/go-modules","title":"Go modules","type":"tag","url":"https://aidanbae.github.io/tags/go-modules"},{"iconClass":"fa-tag","objectID":"https://aidanbae.github.io/tags/gocd","title":"Gocd","type":"tag","url":"https://aidanbae.github.io/tags/gocd"},{"iconClass":"fa-tag","objectID":"https://aidanbae.github.io/tags/gogc","title":"Gogc","type":"tag","url":"https://aidanbae.github.io/tags/gogc"},{"iconClass":"fa-tag","objectID":"https://aidanbae.github.io/tags/golang","title":"Golang","type":"tag","url":"https://aidanbae.github.io/tags/golang"},{"iconClass":"fa-tag","objectID":"https://aidanbae.github.io/tags/google-codejam","title":"Google codejam","type":"tag","url":"https://aidanbae.github.io/tags/google-codejam"},{"iconClass":"fa-tag","objectID":"https://aidanbae.github.io/tags/gravity","title":"Gravity","type":"tag","url":"https://aidanbae.github.io/tags/gravity"},{"iconClass":"fa-tag","objectID":"https://aidanbae.github.io/tags/header","title":"Header","type":"tag","url":"https://aidanbae.github.io/tags/header"},{"iconClass":"fa-tag","objectID":"https://aidanbae.github.io/tags/heap","title":"Heap","type":"tag","url":"https://aidanbae.github.io/tags/heap"},{"iconClass":"fa-tag","objectID":"https://aidanbae.github.io/tags/honne","title":"Honne","type":"tag","url":"https://aidanbae.github.io/tags/honne"},{"iconClass":"fa-tag","objectID":"https://aidanbae.github.io/tags/hope","title":"Hope","type":"tag","url":"https://aidanbae.github.io/tags/hope"},{"iconClass":"fa-tag","objectID":"https://aidanbae.github.io/tags/hugo","title":"Hugo","type":"tag","url":"https://aidanbae.github.io/tags/hugo"},{"iconClass":"fa-tag","objectID":"https://aidanbae.github.io/tags/infra","title":"Infra","type":"tag","url":"https://aidanbae.github.io/tags/infra"},{"iconClass":"fa-tag","objectID":"https://aidanbae.github.io/tags/interface","title":"Interface","type":"tag","url":"https://aidanbae.github.io/tags/interface"},{"iconClass":"fa-tag","objectID":"https://aidanbae.github.io/tags/istio","title":"Istio","type":"tag","url":"https://aidanbae.github.io/tags/istio"},{"iconClass":"fa-tag","objectID":"https://aidanbae.github.io/tags/javascript","title":"Javascript","type":"tag","url":"https://aidanbae.github.io/tags/javascript"},{"iconClass":"fa-tag","objectID":"https://aidanbae.github.io/tags/just-jerk","title":"Just jerk","type":"tag","url":"https://aidanbae.github.io/tags/just-jerk"},{"iconClass":"fa-tag","objectID":"https://aidanbae.github.io/tags/kubernetes","title":"Kubernetes","type":"tag","url":"https://aidanbae.github.io/tags/kubernetes"},{"iconClass":"fa-tag","objectID":"https://aidanbae.github.io/tags/lana-del-rey","title":"Lana del rey","type":"tag","url":"https://aidanbae.github.io/tags/lana-del-rey"},{"iconClass":"fa-tag","objectID":"https://aidanbae.github.io/tags/linux","title":"Linux","type":"tag","url":"https://aidanbae.github.io/tags/linux"},{"iconClass":"fa-tag","objectID":"https://aidanbae.github.io/tags/malloc","title":"Malloc","type":"tag","url":"https://aidanbae.github.io/tags/malloc"},{"iconClass":"fa-tag","objectID":"https://aidanbae.github.io/tags/map","title":"Map","type":"tag","url":"https://aidanbae.github.io/tags/map"},{"iconClass":"fa-tag","objectID":"https://aidanbae.github.io/tags/marathon","title":"Marathon","type":"tag","url":"https://aidanbae.github.io/tags/marathon"},{"iconClass":"fa-tag","objectID":"https://aidanbae.github.io/tags/mesos","title":"Mesos","type":"tag","url":"https://aidanbae.github.io/tags/mesos"},{"iconClass":"fa-tag","objectID":"https://aidanbae.github.io/tags/mesos-marathon","title":"Mesos marathon","type":"tag","url":"https://aidanbae.github.io/tags/mesos-marathon"},{"iconClass":"fa-tag","objectID":"https://aidanbae.github.io/tags/mixer","title":"Mixer","type":"tag","url":"https://aidanbae.github.io/tags/mixer"},{"iconClass":"fa-tag","objectID":"https://aidanbae.github.io/tags/msa","title":"Msa","type":"tag","url":"https://aidanbae.github.io/tags/msa"},{"iconClass":"fa-tag","objectID":"https://aidanbae.github.io/tags/netstat","title":"Netstat","type":"tag","url":"https://aidanbae.github.io/tags/netstat"},{"iconClass":"fa-tag","objectID":"https://aidanbae.github.io/tags/ngrinder","title":"Ngrinder","type":"tag","url":"https://aidanbae.github.io/tags/ngrinder"},{"iconClass":"fa-tag","objectID":"https://aidanbae.github.io/tags/ngrinder-agent","title":"Ngrinder agent","type":"tag","url":"https://aidanbae.github.io/tags/ngrinder-agent"},{"iconClass":"fa-tag","objectID":"https://aidanbae.github.io/tags/ngrinder-controller","title":"Ngrinder controller","type":"tag","url":"https://aidanbae.github.io/tags/ngrinder-controller"},{"iconClass":"fa-tag","objectID":"https://aidanbae.github.io/tags/nsenter","title":"Nsenter","type":"tag","url":"https://aidanbae.github.io/tags/nsenter"},{"iconClass":"fa-tag","objectID":"https://aidanbae.github.io/tags/oro","title":"Oro","type":"tag","url":"https://aidanbae.github.io/tags/oro"},{"iconClass":"fa-tag","objectID":"https://aidanbae.github.io/tags/pac-odd","title":"Pac odd","type":"tag","url":"https://aidanbae.github.io/tags/pac-odd"},{"iconClass":"fa-tag","objectID":"https://aidanbae.github.io/tags/permission","title":"Permission","type":"tag","url":"https://aidanbae.github.io/tags/permission"},{"iconClass":"fa-tag","objectID":"https://aidanbae.github.io/tags/python","title":"Python","type":"tag","url":"https://aidanbae.github.io/tags/python"},{"iconClass":"fa-tag","objectID":"https://aidanbae.github.io/tags/redirection","title":"Redirection","type":"tag","url":"https://aidanbae.github.io/tags/redirection"},{"iconClass":"fa-tag","objectID":"https://aidanbae.github.io/tags/reduce","title":"Reduce","type":"tag","url":"https://aidanbae.github.io/tags/reduce"},{"iconClass":"fa-tag","objectID":"https://aidanbae.github.io/tags/server","title":"Server","type":"tag","url":"https://aidanbae.github.io/tags/server"},{"iconClass":"fa-tag","objectID":"https://aidanbae.github.io/tags/shell-script","title":"Shell script","type":"tag","url":"https://aidanbae.github.io/tags/shell-script"},{"iconClass":"fa-tag","objectID":"https://aidanbae.github.io/tags/slice","title":"Slice","type":"tag","url":"https://aidanbae.github.io/tags/slice"},{"iconClass":"fa-tag","objectID":"https://aidanbae.github.io/tags/sort","title":"Sort","type":"tag","url":"https://aidanbae.github.io/tags/sort"},{"iconClass":"fa-tag","objectID":"https://aidanbae.github.io/tags/soundcloud","title":"Soundcloud","type":"tag","url":"https://aidanbae.github.io/tags/soundcloud"},{"iconClass":"fa-tag","objectID":"https://aidanbae.github.io/tags/struct","title":"Struct","type":"tag","url":"https://aidanbae.github.io/tags/struct"},{"iconClass":"fa-tag","objectID":"https://aidanbae.github.io/tags/tcmalloc","title":"Tcmalloc","type":"tag","url":"https://aidanbae.github.io/tags/tcmalloc"},{"iconClass":"fa-tag","objectID":"https://aidanbae.github.io/tags/tcp","title":"Tcp","type":"tag","url":"https://aidanbae.github.io/tags/tcp"},{"iconClass":"fa-tag","objectID":"https://aidanbae.github.io/tags/tutorial","title":"Tutorial","type":"tag","url":"https://aidanbae.github.io/tags/tutorial"},{"iconClass":"fa-tag","objectID":"https://aidanbae.github.io/tags/validate","title":"Validate","type":"tag","url":"https://aidanbae.github.io/tags/validate"},{"iconClass":"fa-tag","objectID":"https://aidanbae.github.io/tags/vankushuma","title":"Vankushuma","type":"tag","url":"https://aidanbae.github.io/tags/vankushuma"},{"iconClass":"fa-tag","objectID":"https://aidanbae.github.io/tags/websocket","title":"Websocket","type":"tag","url":"https://aidanbae.github.io/tags/websocket"},{"iconClass":"fa-tag","objectID":"https://aidanbae.github.io/tags/who","title":"Who","type":"tag","url":"https://aidanbae.github.io/tags/who"},{"iconClass":"fa-tag","objectID":"https://aidanbae.github.io/tags/x-forwarded","title":"X forwarded","type":"tag","url":"https://aidanbae.github.io/tags/x-forwarded"},{"iconClass":"fa-tag","objectID":"https://aidanbae.github.io/tags/yes-i-know","title":"Yes i know","type":"tag","url":"https://aidanbae.github.io/tags/yes-i-know"},{"iconClass":"fa-tag","objectID":"https://aidanbae.github.io/tags/you","title":"You","type":"tag","url":"https://aidanbae.github.io/tags/you"},{"iconClass":"fa-tag","objectID":"https://aidanbae.github.io/tags/young-and-beautiful","title":"Young and beautiful","type":"tag","url":"https://aidanbae.github.io/tags/young-and-beautiful"},{"iconClass":"fa-tag","objectID":"https://aidanbae.github.io/tags/%EA%B0%90%EC%A0%95%EC%A0%9C%EC%96%B4","title":"감정제어","type":"tag","url":"https://aidanbae.github.io/tags/%EA%B0%90%EC%A0%95%EC%A0%9C%EC%96%B4"},{"iconClass":"fa-tag","objectID":"https://aidanbae.github.io/tags/%EA%B3%A0%EC%98%81%EC%84%B1","title":"고영성","type":"tag","url":"https://aidanbae.github.io/tags/%EA%B3%A0%EC%98%81%EC%84%B1"},{"iconClass":"fa-tag","objectID":"https://aidanbae.github.io/tags/%EA%B3%B5%EC%9C%A0%EB%A9%94%EB%AA%A8%EB%A6%AC","title":"공유메모리","type":"tag","url":"https://aidanbae.github.io/tags/%EA%B3%B5%EC%9C%A0%EB%A9%94%EB%AA%A8%EB%A6%AC"},{"iconClass":"fa-tag","objectID":"https://aidanbae.github.io/tags/%EA%B5%AC%EA%B8%80%EC%BD%94%EB%93%9C%EC%9E%BC","title":"구글코드잼","type":"tag","url":"https://aidanbae.github.io/tags/%EA%B5%AC%EA%B8%80%EC%BD%94%EB%93%9C%EC%9E%BC"},{"iconClass":"fa-tag","objectID":"https://aidanbae.github.io/tags/%EA%B5%BF","title":"굿","type":"tag","url":"https://aidanbae.github.io/tags/%EA%B5%BF"},{"iconClass":"fa-tag","objectID":"https://aidanbae.github.io/tags/%EA%B7%B8%EB%A6%B0%EB%B6%81","title":"그린북","type":"tag","url":"https://aidanbae.github.io/tags/%EA%B7%B8%EB%A6%B0%EB%B6%81"},{"iconClass":"fa-tag","objectID":"https://aidanbae.github.io/tags/%EA%B8%80%EC%93%B0%EA%B8%B0","title":"글쓰기","type":"tag","url":"https://aidanbae.github.io/tags/%EA%B8%80%EC%93%B0%EA%B8%B0"},{"iconClass":"fa-tag","objectID":"https://aidanbae.github.io/tags/%EB%85%BC%EC%9D%98","title":"논의","type":"tag","url":"https://aidanbae.github.io/tags/%EB%85%BC%EC%9D%98"},{"iconClass":"fa-tag","objectID":"https://aidanbae.github.io/tags/%EB%85%BC%EC%9F%81","title":"논쟁","type":"tag","url":"https://aidanbae.github.io/tags/%EB%85%BC%EC%9F%81"},{"iconClass":"fa-tag","objectID":"https://aidanbae.github.io/tags/%EB%8D%94-%ED%91%B8%EB%A5%B8-%ED%92%80","title":"더 푸른 풀","type":"tag","url":"https://aidanbae.github.io/tags/%EB%8D%94-%ED%91%B8%EB%A5%B8-%ED%92%80"},{"iconClass":"fa-tag","objectID":"https://aidanbae.github.io/tags/%EB%A5%98%EC%8B%9C%ED%99%94","title":"류시화","type":"tag","url":"https://aidanbae.github.io/tags/%EB%A5%98%EC%8B%9C%ED%99%94"},{"iconClass":"fa-tag","objectID":"https://aidanbae.github.io/tags/%EB%A6%AC%EB%88%85%EC%8A%A4","title":"리눅스","type":"tag","url":"https://aidanbae.github.io/tags/%EB%A6%AC%EB%88%85%EC%8A%A4"},{"iconClass":"fa-tag","objectID":"https://aidanbae.github.io/tags/%EB%AC%B8%EC%A0%9C%ED%95%B4%EA%B2%B0","title":"문제해결","type":"tag","url":"https://aidanbae.github.io/tags/%EB%AC%B8%EC%A0%9C%ED%95%B4%EA%B2%B0"},{"iconClass":"fa-tag","objectID":"https://aidanbae.github.io/tags/%EB%AC%BC%EB%B3%91","title":"물병","type":"tag","url":"https://aidanbae.github.io/tags/%EB%AC%BC%EB%B3%91"},{"iconClass":"fa-tag","objectID":"https://aidanbae.github.io/tags/%EB%B0%B0%EB%A0%A4","title":"배려","type":"tag","url":"https://aidanbae.github.io/tags/%EB%B0%B0%EB%A0%A4"},{"iconClass":"fa-tag","objectID":"https://aidanbae.github.io/tags/%EB%B9%84%EC%9D%B5%EB%A0%A8%EB%A6%AC","title":"비익련리","type":"tag","url":"https://aidanbae.github.io/tags/%EB%B9%84%EC%9D%B5%EB%A0%A8%EB%A6%AC"},{"iconClass":"fa-tag","objectID":"https://aidanbae.github.io/tags/%EB%B9%85%EC%98%A4%ED%91%9C%EA%B8%B0%EB%B2%95","title":"빅오표기법","type":"tag","url":"https://aidanbae.github.io/tags/%EB%B9%85%EC%98%A4%ED%91%9C%EA%B8%B0%EB%B2%95"},{"iconClass":"fa-tag","objectID":"https://aidanbae.github.io/tags/%EC%82%AC%EB%9E%91","title":"사랑","type":"tag","url":"https://aidanbae.github.io/tags/%EC%82%AC%EB%9E%91"},{"iconClass":"fa-tag","objectID":"https://aidanbae.github.io/tags/%EC%84%9C%EB%B9%84%EC%8A%A4","title":"서비스","type":"tag","url":"https://aidanbae.github.io/tags/%EC%84%9C%EB%B9%84%EC%8A%A4"},{"iconClass":"fa-tag","objectID":"https://aidanbae.github.io/tags/%EC%89%98","title":"쉘","type":"tag","url":"https://aidanbae.github.io/tags/%EC%89%98"},{"iconClass":"fa-tag","objectID":"https://aidanbae.github.io/tags/%EC%89%98-%EC%8A%A4%ED%81%AC%EB%A6%BD%ED%8A%B8","title":"쉘 스크립트","type":"tag","url":"https://aidanbae.github.io/tags/%EC%89%98-%EC%8A%A4%ED%81%AC%EB%A6%BD%ED%8A%B8"},{"iconClass":"fa-tag","objectID":"https://aidanbae.github.io/tags/%EC%8B%9C%EB%A1%9C-%EB%82%A9%EC%B9%98%ED%95%98%EB%8B%A4","title":"시로 납치하다","type":"tag","url":"https://aidanbae.github.io/tags/%EC%8B%9C%EB%A1%9C-%EB%82%A9%EC%B9%98%ED%95%98%EB%8B%A4"},{"iconClass":"fa-tag","objectID":"https://aidanbae.github.io/tags/%EC%95%8C%EA%B3%A0%EB%A6%AC%EC%A6%98","title":"알고리즘","type":"tag","url":"https://aidanbae.github.io/tags/%EC%95%8C%EA%B3%A0%EB%A6%AC%EC%A6%98"},{"iconClass":"fa-tag","objectID":"https://aidanbae.github.io/tags/%EC%95%8C%EA%B3%A0%EB%A6%AC%EC%A6%98-%EB%8F%84%EA%B0%90","title":"알고리즘 도감","type":"tag","url":"https://aidanbae.github.io/tags/%EC%95%8C%EA%B3%A0%EB%A6%AC%EC%A6%98-%EB%8F%84%EA%B0%90"},{"iconClass":"fa-tag","objectID":"https://aidanbae.github.io/tags/%EC%96%B4%EB%A5%B8","title":"어른","type":"tag","url":"https://aidanbae.github.io/tags/%EC%96%B4%EB%A5%B8"},{"iconClass":"fa-tag","objectID":"https://aidanbae.github.io/tags/%EC%97%90%EB%A6%B0-%ED%95%B8%EC%8A%A8","title":"에린 핸슨","type":"tag","url":"https://aidanbae.github.io/tags/%EC%97%90%EB%A6%B0-%ED%95%B8%EC%8A%A8"},{"iconClass":"fa-tag","objectID":"https://aidanbae.github.io/tags/%EC%97%B0%EC%82%B0%EC%9E%90-%EC%98%A4%EB%B2%84%EB%A1%9C%EB%94%A9","title":"연산자 오버로딩","type":"tag","url":"https://aidanbae.github.io/tags/%EC%97%B0%EC%82%B0%EC%9E%90-%EC%98%A4%EB%B2%84%EB%A1%9C%EB%94%A9"},{"iconClass":"fa-tag","objectID":"https://aidanbae.github.io/tags/%EC%99%80%EC%9D%B4%EC%96%B4%EC%83%A4%ED%81%AC","title":"와이어샤크","type":"tag","url":"https://aidanbae.github.io/tags/%EC%99%80%EC%9D%B4%EC%96%B4%EC%83%A4%ED%81%AC"},{"iconClass":"fa-tag","objectID":"https://aidanbae.github.io/tags/%EC%9A%B0%EB%B6%84%ED%88%AC","title":"우분투","type":"tag","url":"https://aidanbae.github.io/tags/%EC%9A%B0%EB%B6%84%ED%88%AC"},{"iconClass":"fa-tag","objectID":"https://aidanbae.github.io/tags/%EC%9A%B0%EC%84%A0%EC%88%9C%EC%9C%84-%ED%81%90","title":"우선순위 큐","type":"tag","url":"https://aidanbae.github.io/tags/%EC%9A%B0%EC%84%A0%EC%88%9C%EC%9C%84-%ED%81%90"},{"iconClass":"fa-tag","objectID":"https://aidanbae.github.io/tags/%EC%9A%B4%EB%AA%85%EB%A1%A0%E3%85%82%EC%9E%90","title":"운명론ㅂ자","type":"tag","url":"https://aidanbae.github.io/tags/%EC%9A%B4%EB%AA%85%EB%A1%A0%E3%85%82%EC%9E%90"},{"iconClass":"fa-tag","objectID":"https://aidanbae.github.io/tags/%EC%9C%84%EB%8C%80%ED%95%9C-%EA%B0%9C%EC%B8%A0%EB%B9%84","title":"위대한 개츠비","type":"tag","url":"https://aidanbae.github.io/tags/%EC%9C%84%EB%8C%80%ED%95%9C-%EA%B0%9C%EC%B8%A0%EB%B9%84"},{"iconClass":"fa-tag","objectID":"https://aidanbae.github.io/tags/%EC%9C%A0%EC%8B%9C%EB%AF%BC","title":"유시민","type":"tag","url":"https://aidanbae.github.io/tags/%EC%9C%A0%EC%8B%9C%EB%AF%BC"},{"iconClass":"fa-tag","objectID":"https://aidanbae.github.io/tags/%EC%9D%B8%EA%B0%84%EA%B4%80%EA%B3%84","title":"인간관계","type":"tag","url":"https://aidanbae.github.io/tags/%EC%9D%B8%EA%B0%84%EA%B4%80%EA%B3%84"},{"iconClass":"fa-tag","objectID":"https://aidanbae.github.io/tags/%EC%9E%90%EB%B0%94%EC%8A%A4%ED%81%AC%EB%A6%BD%ED%8A%B8","title":"자바스크립트","type":"tag","url":"https://aidanbae.github.io/tags/%EC%9E%90%EB%B0%94%EC%8A%A4%ED%81%AC%EB%A6%BD%ED%8A%B8"},{"iconClass":"fa-tag","objectID":"https://aidanbae.github.io/tags/%EC%A0%95%EB%A0%AC","title":"정렬","type":"tag","url":"https://aidanbae.github.io/tags/%EC%A0%95%EB%A0%AC"},{"iconClass":"fa-tag","objectID":"https://aidanbae.github.io/tags/%EC%A0%95%EC%A4%80%EC%9D%BC","title":"정준일","type":"tag","url":"https://aidanbae.github.io/tags/%EC%A0%95%EC%A4%80%EC%9D%BC"},{"iconClass":"fa-tag","objectID":"https://aidanbae.github.io/tags/%EC%A1%B0%EC%96%B8","title":"조언","type":"tag","url":"https://aidanbae.github.io/tags/%EC%A1%B0%EC%96%B8"},{"iconClass":"fa-tag","objectID":"https://aidanbae.github.io/tags/%EC%B2%AD%EC%B6%98","title":"청춘","type":"tag","url":"https://aidanbae.github.io/tags/%EC%B2%AD%EC%B6%98"},{"iconClass":"fa-tag","objectID":"https://aidanbae.github.io/tags/%EC%B2%B4%EC%9D%B8%EC%A7%80-%EA%B7%B8%EB%9D%BC%EC%9A%B4%EB%93%9C","title":"체인지 그라운드","type":"tag","url":"https://aidanbae.github.io/tags/%EC%B2%B4%EC%9D%B8%EC%A7%80-%EA%B7%B8%EB%9D%BC%EC%9A%B4%EB%93%9C"},{"iconClass":"fa-tag","objectID":"https://aidanbae.github.io/tags/%EC%BA%90%EC%8B%9C%EB%9D%BC%EC%9D%B8","title":"캐시라인","type":"tag","url":"https://aidanbae.github.io/tags/%EC%BA%90%EC%8B%9C%EB%9D%BC%EC%9D%B8"},{"iconClass":"fa-tag","objectID":"https://aidanbae.github.io/tags/%EC%BB%A4%EB%84%90","title":"커널","type":"tag","url":"https://aidanbae.github.io/tags/%EC%BB%A4%EB%84%90"},{"iconClass":"fa-tag","objectID":"https://aidanbae.github.io/tags/%EC%BD%94%EC%96%B4","title":"코어","type":"tag","url":"https://aidanbae.github.io/tags/%EC%BD%94%EC%96%B4"},{"iconClass":"fa-tag","objectID":"https://aidanbae.github.io/tags/%ED%81%AC%ED%9D%A0","title":"크흠","type":"tag","url":"https://aidanbae.github.io/tags/%ED%81%AC%ED%9D%A0"},{"iconClass":"fa-tag","objectID":"https://aidanbae.github.io/tags/%ED%87%B4%EC%82%AC","title":"퇴사","type":"tag","url":"https://aidanbae.github.io/tags/%ED%87%B4%EC%82%AC"},{"iconClass":"fa-tag","objectID":"https://aidanbae.github.io/tags/%ED%8A%B9%EB%B3%84%EB%A9%94%EC%84%9C%EB%93%9C","title":"특별메서드","type":"tag","url":"https://aidanbae.github.io/tags/%ED%8A%B9%EB%B3%84%EB%A9%94%EC%84%9C%EB%93%9C"},{"iconClass":"fa-tag","objectID":"https://aidanbae.github.io/tags/%ED%95%9C%EC%88%A8","title":"한숨","type":"tag","url":"https://aidanbae.github.io/tags/%ED%95%9C%EC%88%A8"},{"iconClass":"fa-tag","objectID":"https://aidanbae.github.io/tags/%ED%95%AD%EC%86%8C%EC%9D%B4%EC%9C%A0%EC%84%9C","title":"항소이유서","type":"tag","url":"https://aidanbae.github.io/tags/%ED%95%AD%EC%86%8C%EC%9D%B4%EC%9C%A0%EC%84%9C"},{"iconClass":"fa-tag","objectID":"https://aidanbae.github.io/tags/%ED%9D%94%EB%93%A4%EB%A6%BC","title":"흔들림","type":"tag","url":"https://aidanbae.github.io/tags/%ED%9D%94%EB%93%A4%EB%A6%BC"},{"author":null,"categories":null,"iconClass":"fa-pencil","language":"en","objectID":"f38c5535c6e7fa5e04723092b8d6cb42","tags":null,"title":"Codes","type":"code","url":"https://aidanbae.github.io/code/"},{"author":null,"categories":null,"iconClass":"fa-music","language":"en","objectID":"d98dabd6546423c18fa4fe727c27a7da","tags":null,"title":"Audios","type":"audio","url":"https://aidanbae.github.io/audio/"},{"author":null,"categories":null,"iconClass":"fa-pencil","language":"en","objectID":"7b677140e0c1697e1a82fe9871df3c58","tags":null,"title":"Articles","type":"article","url":"https://aidanbae.github.io/article/"},{"author":null,"categories":null,"iconClass":"fa-video-camera","language":"en","objectID":"cced299dc4ee5368ce0110c47ab6ace1","tags":null,"title":"Videos","type":"video","url":"https://aidanbae.github.io/video/"},{"author":null,"categories":null,"iconClass":"fa-quote-right","language":"en","objectID":"42ad3f6ab8799dd06c0b7008f1296f48","tags":null,"title":"Quotes","type":"quote","url":"https://aidanbae.github.io/quote/"},{"author":null,"categories":null,"iconClass":"fa-camera","language":"en","objectID":"117f0d217857409382ca8e0832679898","tags":null,"title":"Galleries","type":"gallery","url":"https://aidanbae.github.io/gallery/"}]